wiki_emailer/Emailer.py
wiki_emailer/__init__.py
wiki_emailer-2.0.dist-info/DESCRIPTION.rst
wiki_emailer-2.0.dist-info/METADATA
wiki_emailer-2.0.dist-info/RECORD
wiki_emailer-2.0.dist-info/WHEEL
wiki_emailer-2.0.dist-info/metadata.json
wiki_emailer-2.0.dist-info/top_level.txt
