Metadata-Version: 2.0
Name: wiki-emailer
Version: 2.0
Summary: Convert a markdown file to pdf and sends it via email
Home-page: UNKNOWN
Author: Steve Brownfield
Author-email: brownfiels2@nku.edu
License: UNKNOWN
Platform: UNKNOWN
Requires-Dist: pypandoc
